nb_py/__init__.py
nb_py/compute.py
nb_py-0.1.3.data/data/requirements-dev.txt
nb_py-0.1.3.data/data/requirements.txt
nb_py-0.1.3.dist-info/LICENSE
nb_py-0.1.3.dist-info/METADATA
nb_py-0.1.3.dist-info/WHEEL
nb_py-0.1.3.dist-info/top_level.txt
nb_py-0.1.3.dist-info/RECORD
